parameterframe/__init__.py
parameterframe/parameterframe.py
parameterframe/setup.py
parameterframe-0.1.6.dist-info/LICENSE
parameterframe-0.1.6.dist-info/METADATA
parameterframe-0.1.6.dist-info/WHEEL
parameterframe-0.1.6.dist-info/top_level.txt
parameterframe-0.1.6.dist-info/RECORD
