Metadata-Version: 2.1
Name: parameterframe
Version: 0.1.6
Summary: A tool to manage parameters in a form of files, process them, upload to param storage, pull and reconstrut as files.
Author: Kyrylo Mordan
Author-email: parachute.repo@gmail.com
Keywords: ['python','parameter storage']
Classifier: Development Status :: 3 - Alpha
Classifier: Intended Audience :: Developers
Classifier: Intended Audience :: Science/Research
Classifier: Programming Language :: Python :: 3
Classifier: Programming Language :: Python :: 3.9
Classifier: Programming Language :: Python :: 3.10
Classifier: Programming Language :: Python :: 3.11
Classifier: License :: OSI Approved :: MIT License
Classifier: Topic :: Scientific/Engineering
License-File: LICENSE
Requires-Dist: attrs
Requires-Dist: pyyaml
Requires-Dist: mocker-db ==0.1.1
Requires-Dist: cryptography
Requires-Dist: dill
Requires-Dist: pandas
Requires-Dist: sqlalchemy
